vault_env/__init__.py
vault_env/main.py
pyvaultenv-1.1.4.dist-info/METADATA
pyvaultenv-1.1.4.dist-info/WHEEL
pyvaultenv-1.1.4.dist-info/entry_points.txt
pyvaultenv-1.1.4.dist-info/RECORD
